django_registration/__init__.py
django_registration/exceptions.py
django_registration/forms.py
django_registration/signals.py
django_registration/validators.py
django_registration/views.py
django_registration/backends/__init__.py
django_registration/backends/activation/__init__.py
django_registration/backends/activation/urls.py
django_registration/backends/activation/views.py
django_registration/backends/one_step/__init__.py
django_registration/backends/one_step/urls.py
django_registration/backends/one_step/views.py
django_registration/locale/ar/LC_MESSAGES/django.mo
django_registration/locale/ar/LC_MESSAGES/django.po
django_registration/locale/bg/LC_MESSAGES/django.mo
django_registration/locale/bg/LC_MESSAGES/django.po
django_registration/locale/ca/LC_MESSAGES/django.mo
django_registration/locale/ca/LC_MESSAGES/django.po
django_registration/locale/cs/LC_MESSAGES/django.mo
django_registration/locale/cs/LC_MESSAGES/django.po
django_registration/locale/da/LC_MESSAGES/django.mo
django_registration/locale/da/LC_MESSAGES/django.po
django_registration/locale/de/LC_MESSAGES/django.mo
django_registration/locale/de/LC_MESSAGES/django.po
django_registration/locale/el/LC_MESSAGES/django.mo
django_registration/locale/el/LC_MESSAGES/django.po
django_registration/locale/en/LC_MESSAGES/django.mo
django_registration/locale/en/LC_MESSAGES/django.po
django_registration/locale/es/LC_MESSAGES/django.mo
django_registration/locale/es/LC_MESSAGES/django.po
django_registration/locale/es_AR/LC_MESSAGES/django.mo
django_registration/locale/es_AR/LC_MESSAGES/django.po
django_registration/locale/fa/LC_MESSAGES/django.mo
django_registration/locale/fa/LC_MESSAGES/django.po
django_registration/locale/fr/LC_MESSAGES/django.mo
django_registration/locale/fr/LC_MESSAGES/django.po
django_registration/locale/he/LC_MESSAGES/django.mo
django_registration/locale/he/LC_MESSAGES/django.po
django_registration/locale/hr/LC_MESSAGES/django.mo
django_registration/locale/hr/LC_MESSAGES/django.po
django_registration-3.4.dist-info/AUTHORS
django_registration-3.4.dist-info/LICENSE
django_registration-3.4.dist-info/METADATA
django_registration-3.4.dist-info/WHEEL
django_registration-3.4.dist-info/top_level.txt
django_registration-3.4.dist-info/RECORD
