Metadata-Version: 2.1
Name: django-registration
Version: 3.4
Summary: An extensible user-registration application for Django.
Author-email: James Bennett <james@b-list.org>
License: BSD-3-Clause
Project-URL: documentation, https://django-registration.readthedocs.io/
Project-URL: homepage, https://github.com/ubernostrum/django-registration
Keywords: django,security,auth,authentication
Classifier: Development Status :: 5 - Production/Stable
Classifier: Environment :: Web Environment
Classifier: Framework :: Django
Classifier: Framework :: Django :: 3.2
Classifier: Framework :: Django :: 4.1
Classifier: Framework :: Django :: 4.2
Classifier: Intended Audience :: Developers
Classifier: License :: OSI Approved :: BSD License
Classifier: Operating System :: OS Independent
Classifier: Programming Language :: Python
Classifier: Programming Language :: Python :: 3
Classifier: Programming Language :: Python :: 3.7
Classifier: Programming Language :: Python :: 3.8
Classifier: Programming Language :: Python :: 3.9
Classifier: Programming Language :: Python :: 3.10
Classifier: Programming Language :: Python :: 3.11
Classifier: Topic :: Utilities
Requires-Python: >=3.7
Provides-Extra: docs
Provides-Extra: tests
License-File: LICENSE
License-File: AUTHORS
